enveil/__init__.py
enveil/api.py
enveil/main.py
enveil/collectors/__init__.py
enveil/collectors/base_collector.py
enveil/collectors/hardware_collector.py
enveil/collectors/os_collector.py
enveil/collectors/software_collector.py
enveil/config/__init__.py
enveil/config/config_manager.py
enveil/config/default_software.py
enveil/core/__init__.py
enveil/core/command_executor.py
enveil/core/data_formatter.py
enveil/core/platform_detector.py
enveil/utils/__init__.py
enveil/utils/exceptions.py
enveil/utils/security.py
enveil-1.0.0.dist-info/licenses/LICENSE
enveil-1.0.0.dist-info/METADATA
enveil-1.0.0.dist-info/WHEEL
enveil-1.0.0.dist-info/entry_points.txt
enveil-1.0.0.dist-info/top_level.txt
enveil-1.0.0.dist-info/RECORD
