Metadata-Version: 2.4
Name: enveil
Version: 1.0.0
Summary: A secure, cross-platform tool to gather system environment information (hardware, OS, software).
Author-email: FlatBone <151115967+FlatBone@users.noreply.github.com>
License: MIT License
Project-URL: Homepage, https://github.com/FlatBone/Enveil
Project-URL: Issues, https://github.com/FlatBone/Enveil/issues
Keywords: environment,system,information,hardware,os,software,cli
Classifier: Development Status :: 3 - Alpha
Classifier: Intended Audience :: Developers
Classifier: Intended Audience :: System Administrators
Classifier: License :: OSI Approved :: MIT License
Classifier: Operating System :: OS Independent
Classifier: Programming Language :: Python :: 3
Classifier: Programming Language :: Python :: 3.8
Classifier: Programming Language :: Python :: 3.9
Classifier: Programming Language :: Python :: 3.10
Classifier: Programming Language :: Python :: 3.11
Classifier: Topic :: System :: Systems Administration
Classifier: Topic :: Utilities
Requires-Python: >=3.8
License-File: LICENSE
Dynamic: license-file
